[{"id":130566,"guid":"917eb1b9-29c9-cdec-7dfd-a273b899ea17","pyramid":"LIDAR-DSM-1M-ENGLAND-2006-EA","tileReference":"SS51","fileName":"LIDAR-DSM-1M-2006-SS51.zip","coverageLayer":"LIDAR-DSM-1M-ENGLAND-2006-EA-MD-YY","fileSize":92537441,"descriptiveName":"LIDAR Tiles DSM at 1m spatial resolution 2006","description":"1m","groupName":"LIDAR-DSM-TIMESTAMPED-ENGLAND-2006-EA","displayOrder":-100,"metaDataUrl":null},{"id":143313,"guid":"1cbedd59-6ee2-4b28-e34a-ac64f9d116eb","pyramid":"LIDAR-DSM-1M-ENGLAND-2015-EA","tileReference":"SS51","fileName":"LIDAR-DSM-1M-2015-SS51.zip","coverageLayer":"LIDAR-DSM-1M-ENGLAND-2015-EA-MD-YY","fileSize":9334949,"descriptiveName":"LIDAR Tiles DSM at 1m spatial resolution 2015","description":"1m","groupName":"LIDAR-DSM-TIMESTAMPED-ENGLAND-2015-EA","displayOrder":-100,"metaDataUrl":null},{"id":143908,"guid":"e7b85eff-9169-a475-a323-7e93af2cfaa0","pyramid":"LIDAR-DSM-1M-ENGLAND-EA","tileReference":"SS51","fileName":"LIDAR-DSM-1M-SS51.zip","coverageLayer":"LIDAR-DSM-1M-ENGLAND-EA-MD-YY","fileSize":89750632,"descriptiveName":"LIDAR Composite DSM - 1m spatial resolution","description":"DSM at 1m spatial resolution","groupName":"LIDAR-DSM-GROUP-ENGLAND-EA","displayOrder":-100,"metaDataUrl":"https://data.gov.uk/dataset/lidar-composite-dsm-1m1"},{"id":146079,"guid":"96f2ee1c-f76c-2cad-97ed-4fe92d020ce9","pyramid":"LIDAR-DSM-2M-ENGLAND-EA","tileReference":"SS51","fileName":"LIDAR-DSM-2M-SS51.zip","coverageLayer":"LIDAR-DSM-2M-ENGLAND-EA-MD-YY","fileSize":27716891,"descriptiveName":"LIDAR Composite DSM - 2m spatial resolution","description":"DSM at 2m spatial resolution","groupName":"LIDAR-DSM-GROUP-ENGLAND-EA","displayOrder":-200,"metaDataUrl":"https://data.gov.uk/dataset/lidar-composite-dsm-2m1"},{"id":128055,"guid":"e1f745f9-3368-2005-984c-6f6933dbbb0a","pyramid":"LIDAR-DTM-1M-ENGLAND-2006-EA","tileReference":"SS51","fileName":"LIDAR-DTM-1M-2006-SS51.zip","coverageLayer":"LIDAR-DTM-1M-ENGLAND-2006-EA-MD-YY","fileSize":101884218,"descriptiveName":"LIDAR Tiles DTM at 1m spatial resolution 2006","description":"1m","groupName":"LIDAR-DTM-TIMESTAMPED-ENGLAND-2006-EA","displayOrder":-100,"metaDataUrl":null},{"id":143617,"guid":"f2050c0c-0125-2f5d-e67a-93f141e9e957","pyramid":"LIDAR-DTM-1M-ENGLAND-2015-EA","tileReference":"SS51","fileName":"LIDAR-DTM-1M-2015-SS51.zip","coverageLayer":"LIDAR-DTM-1M-ENGLAND-2015-EA-MD-YY","fileSize":9387690,"descriptiveName":"LIDAR Tiles DTM at 1m spatial resolution 2015","description":"1m","groupName":"LIDAR-DTM-TIMESTAMPED-ENGLAND-2015-EA","displayOrder":-100,"metaDataUrl":null},{"id":137897,"guid":"96216cb7-3754-1cc4-c9c0-cc7be3fba16f","pyramid":"LIDAR-DTM-1M-ENGLAND-EA","tileReference":"SS51","fileName":"LIDAR-DTM-1M-SS51.zip","coverageLayer":"LIDAR-DTM-1M-ENGLAND-EA-MD-YY","fileSize":84332950,"descriptiveName":"LIDAR Composite DTM - 1m spatial resolution","description":"DTM at 1m spatial resolution","groupName":"LIDAR-DTM-GROUP-ENGLAND-EA","displayOrder":-100,"metaDataUrl":"https://data.gov.uk/dataset/lidar-composite-dtm-1m1"},{"id":137485,"guid":"ad579d6d-ff8d-9f05-db2f-98cc9fb91e14","pyramid":"LIDAR-DTM-2M-ENGLAND-EA","tileReference":"SS51","fileName":"LIDAR-DTM-2M-SS51.zip","coverageLayer":"LIDAR-DTM-2M-ENGLAND-EA-MD-YY","fileSize":27398628,"descriptiveName":"LIDAR Composite DTM - 2m spatial resolution","description":"DTM at 2m spatial resolution","groupName":"LIDAR-DTM-GROUP-ENGLAND-EA","displayOrder":-200,"metaDataUrl":"https://data.gov.uk/dataset/lidar-composite-dtm-2m1"}]