[
    {
        "id": 178412,
        "guid": "b3309c08-b27d-11e6-b565-9457a5578ca0",
        "pyramid": "LIDAR-DSM-1M-ENGLAND-2005-EA",
        "tileReference": "TQ46",
        "fileName": "LIDAR-DSM-1M-2005-TQ4060.zip",
        "coverageLayer": "LIDAR-DSM-1M-ENGLAND-2005-EA-MD-YY",
        "fileSize": 21622926,
        "descriptiveName": "LIDAR Tiles DSM at 1m spatial resolution 2005",
        "description": "1m",
        "groupName": "LIDAR-DSM-TIMESTAMPED-ENGLAND-2005-EA",
        "displayOrder": -100,
        "metaDataUrl": null,
        "url": "http:\/\/www.geostore.com\/environment-agency\/rest\/product\/download\/b3309c08-b27d-11e6-b565-9457a5578ca0"
    },
    {
        "id": 178434,
        "guid": "c47271e4-b27d-11e6-b565-9457a5578ca0",
        "pyramid": "LIDAR-DSM-1M-ENGLAND-2005-EA",
        "tileReference": "TQ46",
        "fileName": "LIDAR-DSM-1M-2005-TQ4065.zip",
        "coverageLayer": "LIDAR-DSM-1M-ENGLAND-2005-EA-MD-YY",
        "fileSize": 62377947,
        "descriptiveName": "LIDAR Tiles DSM at 1m spatial resolution 2005",
        "description": "1m",
        "groupName": "LIDAR-DSM-TIMESTAMPED-ENGLAND-2005-EA",
        "displayOrder": -100,
        "metaDataUrl": null,
        "url": "http:\/\/www.geostore.com\/environment-agency\/rest\/product\/download\/c47271e4-b27d-11e6-b565-9457a5578ca0"
    },
    {
        "id": 178460,
        "guid": "d653babc-b27d-11e6-b565-9457a5578ca0",
        "pyramid": "LIDAR-DSM-1M-ENGLAND-2005-EA",
        "tileReference": "TQ46",
        "fileName": "LIDAR-DSM-1M-2005-TQ4560.zip",
        "coverageLayer": "LIDAR-DSM-1M-ENGLAND-2005-EA-MD-YY",
        "fileSize": 5200181,
        "descriptiveName": "LIDAR Tiles DSM at 1m spatial resolution 2005",
        "description": "1m",
        "groupName": "LIDAR-DSM-TIMESTAMPED-ENGLAND-2005-EA",
        "displayOrder": -100,
        "metaDataUrl": null,
        "url": "http:\/\/www.geostore.com\/environment-agency\/rest\/product\/download\/d653babc-b27d-11e6-b565-9457a5578ca0"
    },
    {
        "id": 178466,
        "guid": "dabde2a8-b27d-11e6-b565-9457a5578ca0",
        "pyramid": "LIDAR-DSM-1M-ENGLAND-2005-EA",
        "tileReference": "TQ46",
        "fileName": "LIDAR-DSM-1M-2005-TQ4565.zip",
        "coverageLayer": "LIDAR-DSM-1M-ENGLAND-2005-EA-MD-YY",
        "fileSize": 17223932,
        "descriptiveName": "LIDAR Tiles DSM at 1m spatial resolution 2005",
        "description": "1m",
        "groupName": "LIDAR-DSM-TIMESTAMPED-ENGLAND-2005-EA",
        "displayOrder": -100,
        "metaDataUrl": null,
        "url": "http:\/\/www.geostore.com\/environment-agency\/rest\/product\/download\/dabde2a8-b27d-11e6-b565-9457a5578ca0"
    },
    {
        "id": 208575,
        "guid": "62f3132c-b2ac-11e6-bcdf-9457a5578ca0",
        "pyramid": "LIDAR-DSM-1M-ENGLAND-2012-EA",
        "tileReference": "TQ46",
        "fileName": "LIDAR-DSM-1M-2012-TQ4560.zip",
        "coverageLayer": "LIDAR-DSM-1M-ENGLAND-2012-EA-MD-YY",
        "fileSize": 3902433,
        "descriptiveName": "LIDAR Tiles DSM at 1m spatial resolution 2012",
        "description": "1m",
        "groupName": "LIDAR-DSM-TIMESTAMPED-ENGLAND-2012-EA",
        "displayOrder": -100,
        "metaDataUrl": null,
        "url": "http:\/\/www.geostore.com\/environment-agency\/rest\/product\/download\/62f3132c-b2ac-11e6-bcdf-9457a5578ca0"
    },
    {
        "id": 208576,
        "guid": "67416050-b2ac-11e6-bcdf-9457a5578ca0",
        "pyramid": "LIDAR-DSM-1M-ENGLAND-2012-EA",
        "tileReference": "TQ46",
        "fileName": "LIDAR-DSM-1M-2012-TQ4565.zip",
        "coverageLayer": "LIDAR-DSM-1M-ENGLAND-2012-EA-MD-YY",
        "fileSize": 16098542,
        "descriptiveName": "LIDAR Tiles DSM at 1m spatial resolution 2012",
        "description": "1m",
        "groupName": "LIDAR-DSM-TIMESTAMPED-ENGLAND-2012-EA",
        "displayOrder": -100,
        "metaDataUrl": null,
        "url": "http:\/\/www.geostore.com\/environment-agency\/rest\/product\/download\/67416050-b2ac-11e6-bcdf-9457a5578ca0"
    },
    {
        "id": 208558,
        "guid": "38964108-b2ac-11e6-bcdf-9457a5578ca0",
        "pyramid": "LIDAR-DSM-1M-ENGLAND-2012-EA",
        "tileReference": "TQ46",
        "fileName": "LIDAR-DSM-1M-2012-TQ4060.zip",
        "coverageLayer": "LIDAR-DSM-1M-ENGLAND-2012-EA-MD-YY",
        "fileSize": 20869376,
        "descriptiveName": "LIDAR Tiles DSM at 1m spatial resolution 2012",
        "description": "1m",
        "groupName": "LIDAR-DSM-TIMESTAMPED-ENGLAND-2012-EA",
        "displayOrder": -100,
        "metaDataUrl": null,
        "url": "http:\/\/www.geostore.com\/environment-agency\/rest\/product\/download\/38964108-b2ac-11e6-bcdf-9457a5578ca0"
    },
    {
        "id": 208559,
        "guid": "47fdd660-b2ac-11e6-bcdf-9457a5578ca0",
        "pyramid": "LIDAR-DSM-1M-ENGLAND-2012-EA",
        "tileReference": "TQ46",
        "fileName": "LIDAR-DSM-1M-2012-TQ4065.zip",
        "coverageLayer": "LIDAR-DSM-1M-ENGLAND-2012-EA-MD-YY",
        "fileSize": 58403376,
        "descriptiveName": "LIDAR Tiles DSM at 1m spatial resolution 2012",
        "description": "1m",
        "groupName": "LIDAR-DSM-TIMESTAMPED-ENGLAND-2012-EA",
        "displayOrder": -100,
        "metaDataUrl": null,
        "url": "http:\/\/www.geostore.com\/environment-agency\/rest\/product\/download\/47fdd660-b2ac-11e6-bcdf-9457a5578ca0"
    },
    {
        "id": 155355,
        "guid": "b92ac0b2-a066-11e6-a934-8cdcd4b4861c",
        "pyramid": "LIDAR-DSM-1M-ENGLAND-2015-EA",
        "tileReference": "TQ46",
        "fileName": "LIDAR-DSM-1M-2015-TQ4060.zip",
        "coverageLayer": "LIDAR-DSM-1M-ENGLAND-2015-EA-MD-YY",
        "fileSize": 50763036,
        "descriptiveName": "LIDAR Tiles DSM at 1m spatial resolution 2015",
        "description": "1m",
        "groupName": "LIDAR-DSM-TIMESTAMPED-ENGLAND-2015-EA",
        "displayOrder": -100,
        "metaDataUrl": null,
        "url": "http:\/\/www.geostore.com\/environment-agency\/rest\/product\/download\/b92ac0b2-a066-11e6-a934-8cdcd4b4861c"
    },
    {
        "id": 155362,
        "guid": "c42e6702-a066-11e6-a934-8cdcd4b4861c",
        "pyramid": "LIDAR-DSM-1M-ENGLAND-2015-EA",
        "tileReference": "TQ46",
        "fileName": "LIDAR-DSM-1M-2015-TQ4065.zip",
        "coverageLayer": "LIDAR-DSM-1M-ENGLAND-2015-EA-MD-YY",
        "fileSize": 44186806,
        "descriptiveName": "LIDAR Tiles DSM at 1m spatial resolution 2015",
        "description": "1m",
        "groupName": "LIDAR-DSM-TIMESTAMPED-ENGLAND-2015-EA",
        "displayOrder": -100,
        "metaDataUrl": null,
        "url": "http:\/\/www.geostore.com\/environment-agency\/rest\/product\/download\/c42e6702-a066-11e6-a934-8cdcd4b4861c"
    },
    {
        "id": 155406,
        "guid": "0e8c2492-a067-11e6-a934-8cdcd4b4861c",
        "pyramid": "LIDAR-DSM-1M-ENGLAND-2015-EA",
        "tileReference": "TQ46",
        "fileName": "LIDAR-DSM-1M-2015-TQ4560.zip",
        "coverageLayer": "LIDAR-DSM-1M-ENGLAND-2015-EA-MD-YY",
        "fileSize": 65539598,
        "descriptiveName": "LIDAR Tiles DSM at 1m spatial resolution 2015",
        "description": "1m",
        "groupName": "LIDAR-DSM-TIMESTAMPED-ENGLAND-2015-EA",
        "displayOrder": -100,
        "metaDataUrl": null,
        "url": "http:\/\/www.geostore.com\/environment-agency\/rest\/product\/download\/0e8c2492-a067-11e6-a934-8cdcd4b4861c"
    },
    {
        "id": 155409,
        "guid": "1e7035ec-a067-11e6-a934-8cdcd4b4861c",
        "pyramid": "LIDAR-DSM-1M-ENGLAND-2015-EA",
        "tileReference": "TQ46",
        "fileName": "LIDAR-DSM-1M-2015-TQ4565.zip",
        "coverageLayer": "LIDAR-DSM-1M-ENGLAND-2015-EA-MD-YY",
        "fileSize": 65123118,
        "descriptiveName": "LIDAR Tiles DSM at 1m spatial resolution 2015",
        "description": "1m",
        "groupName": "LIDAR-DSM-TIMESTAMPED-ENGLAND-2015-EA",
        "displayOrder": -100,
        "metaDataUrl": null,
        "url": "http:\/\/www.geostore.com\/environment-agency\/rest\/product\/download\/1e7035ec-a067-11e6-a934-8cdcd4b4861c"
    },
    {
        "id": 237790,
        "guid": "a409b8ca-ae33-11e6-b6e8-8cdcd4b4861c",
        "pyramid": "LIDAR-DSM-1M-ENGLAND-EA",
        "tileReference": "TQ46",
        "fileName": "LIDAR-DSM-1M-TQ4065.zip",
        "coverageLayer": "LIDAR-DSM-1M-ENGLAND-EA-MD-YY",
        "fileSize": 59753062,
        "descriptiveName": "LIDAR Composite DSM - 1m spatial resolution",
        "description": "DSM at 1m spatial resolution",
        "groupName": "LIDAR-DSM-GROUP-ENGLAND-EA",
        "displayOrder": -100,
        "metaDataUrl": "https:\/\/data.gov.uk\/dataset\/lidar-composite-dsm-1m1",
        "url": "http:\/\/www.geostore.com\/environment-agency\/rest\/product\/download\/a409b8ca-ae33-11e6-b6e8-8cdcd4b4861c"
    },
    {
        "id": 237789,
        "guid": "997f5de2-ae33-11e6-b6e8-8cdcd4b4861c",
        "pyramid": "LIDAR-DSM-1M-ENGLAND-EA",
        "tileReference": "TQ46",
        "fileName": "LIDAR-DSM-1M-TQ4060.zip",
        "coverageLayer": "LIDAR-DSM-1M-ENGLAND-EA-MD-YY",
        "fileSize": 48247259,
        "descriptiveName": "LIDAR Composite DSM - 1m spatial resolution",
        "description": "DSM at 1m spatial resolution",
        "groupName": "LIDAR-DSM-GROUP-ENGLAND-EA",
        "displayOrder": -100,
        "metaDataUrl": "https:\/\/data.gov.uk\/dataset\/lidar-composite-dsm-1m1",
        "url": "http:\/\/www.geostore.com\/environment-agency\/rest\/product\/download\/997f5de2-ae33-11e6-b6e8-8cdcd4b4861c"
    },
    {
        "id": 237810,
        "guid": "5930d512-ae34-11e6-b6e8-8cdcd4b4861c",
        "pyramid": "LIDAR-DSM-1M-ENGLAND-EA",
        "tileReference": "TQ46",
        "fileName": "LIDAR-DSM-1M-TQ4565.zip",
        "coverageLayer": "LIDAR-DSM-1M-ENGLAND-EA-MD-YY",
        "fileSize": 53853394,
        "descriptiveName": "LIDAR Composite DSM - 1m spatial resolution",
        "description": "DSM at 1m spatial resolution",
        "groupName": "LIDAR-DSM-GROUP-ENGLAND-EA",
        "displayOrder": -100,
        "metaDataUrl": "https:\/\/data.gov.uk\/dataset\/lidar-composite-dsm-1m1",
        "url": "http:\/\/www.geostore.com\/environment-agency\/rest\/product\/download\/5930d512-ae34-11e6-b6e8-8cdcd4b4861c"
    },
    {
        "id": 237809,
        "guid": "4faa00c2-ae34-11e6-b6e8-8cdcd4b4861c",
        "pyramid": "LIDAR-DSM-1M-ENGLAND-EA",
        "tileReference": "TQ46",
        "fileName": "LIDAR-DSM-1M-TQ4560.zip",
        "coverageLayer": "LIDAR-DSM-1M-ENGLAND-EA-MD-YY",
        "fileSize": 53638555,
        "descriptiveName": "LIDAR Composite DSM - 1m spatial resolution",
        "description": "DSM at 1m spatial resolution",
        "groupName": "LIDAR-DSM-GROUP-ENGLAND-EA",
        "displayOrder": -100,
        "metaDataUrl": "https:\/\/data.gov.uk\/dataset\/lidar-composite-dsm-1m1",
        "url": "http:\/\/www.geostore.com\/environment-agency\/rest\/product\/download\/4faa00c2-ae34-11e6-b6e8-8cdcd4b4861c"
    },
    {
        "id": 221292,
        "guid": "84d5ce24-a50c-11e6-847b-8cdcd4b4861c",
        "pyramid": "LIDAR-DSM-2M-ENGLAND-EA",
        "tileReference": "TQ46",
        "fileName": "LIDAR-DSM-2M-TQ4560.zip",
        "coverageLayer": "LIDAR-DSM-2M-ENGLAND-EA-MD-YY",
        "fileSize": 14233629,
        "descriptiveName": "LIDAR Composite DSM - 2m spatial resolution",
        "description": "DSM at 2m spatial resolution",
        "groupName": "LIDAR-DSM-GROUP-ENGLAND-EA",
        "displayOrder": -200,
        "metaDataUrl": "https:\/\/data.gov.uk\/dataset\/lidar-composite-dsm-2m1",
        "url": "http:\/\/www.geostore.com\/environment-agency\/rest\/product\/download\/84d5ce24-a50c-11e6-847b-8cdcd4b4861c"
    },
    {
        "id": 221294,
        "guid": "891dcae0-a50c-11e6-847b-8cdcd4b4861c",
        "pyramid": "LIDAR-DSM-2M-ENGLAND-EA",
        "tileReference": "TQ46",
        "fileName": "LIDAR-DSM-2M-TQ4565.zip",
        "coverageLayer": "LIDAR-DSM-2M-ENGLAND-EA-MD-YY",
        "fileSize": 13920143,
        "descriptiveName": "LIDAR Composite DSM - 2m spatial resolution",
        "description": "DSM at 2m spatial resolution",
        "groupName": "LIDAR-DSM-GROUP-ENGLAND-EA",
        "displayOrder": -200,
        "metaDataUrl": "https:\/\/data.gov.uk\/dataset\/lidar-composite-dsm-2m1",
        "url": "http:\/\/www.geostore.com\/environment-agency\/rest\/product\/download\/891dcae0-a50c-11e6-847b-8cdcd4b4861c"
    },
    {
        "id": 221161,
        "guid": "aaf67898-a50b-11e6-847b-8cdcd4b4861c",
        "pyramid": "LIDAR-DSM-2M-ENGLAND-EA",
        "tileReference": "TQ46",
        "fileName": "LIDAR-DSM-2M-TQ4060.zip",
        "coverageLayer": "LIDAR-DSM-2M-ENGLAND-EA-MD-YY",
        "fileSize": 7683533,
        "descriptiveName": "LIDAR Composite DSM - 2m spatial resolution",
        "description": "DSM at 2m spatial resolution",
        "groupName": "LIDAR-DSM-GROUP-ENGLAND-EA",
        "displayOrder": -200,
        "metaDataUrl": "https:\/\/data.gov.uk\/dataset\/lidar-composite-dsm-2m1",
        "url": "http:\/\/www.geostore.com\/environment-agency\/rest\/product\/download\/aaf67898-a50b-11e6-847b-8cdcd4b4861c"
    },
    {
        "id": 221163,
        "guid": "af3bdcb8-a50b-11e6-847b-8cdcd4b4861c",
        "pyramid": "LIDAR-DSM-2M-ENGLAND-EA",
        "tileReference": "TQ46",
        "fileName": "LIDAR-DSM-2M-TQ4065.zip",
        "coverageLayer": "LIDAR-DSM-2M-ENGLAND-EA-MD-YY",
        "fileSize": 13607868,
        "descriptiveName": "LIDAR Composite DSM - 2m spatial resolution",
        "description": "DSM at 2m spatial resolution",
        "groupName": "LIDAR-DSM-GROUP-ENGLAND-EA",
        "displayOrder": -200,
        "metaDataUrl": "https:\/\/data.gov.uk\/dataset\/lidar-composite-dsm-2m1",
        "url": "http:\/\/www.geostore.com\/environment-agency\/rest\/product\/download\/af3bdcb8-a50b-11e6-847b-8cdcd4b4861c"
    },
    {
        "id": 176587,
        "guid": "f431cbce-b281-11e6-a8b2-9457a5578ca0",
        "pyramid": "LIDAR-DSM-50CM-ENGLAND-2009-EA",
        "tileReference": "TQ46",
        "fileName": "LIDAR-DSM-50CM-2009-TQ4065.zip",
        "coverageLayer": "LIDAR-DSM-50CM-ENGLAND-2009-EA-MD-YY",
        "fileSize": 21977914,
        "descriptiveName": "LIDAR Tiles DSM at 50cm spatial resolution 2009",
        "description": "50cm",
        "groupName": "LIDAR-DSM-TIMESTAMPED-ENGLAND-2009-EA",
        "displayOrder": -50,
        "metaDataUrl": null,
        "url": "http:\/\/www.geostore.com\/environment-agency\/rest\/product\/download\/f431cbce-b281-11e6-a8b2-9457a5578ca0"
    },
    {
        "id": 176577,
        "guid": "ed780b0e-b281-11e6-a8b2-9457a5578ca0",
        "pyramid": "LIDAR-DSM-50CM-ENGLAND-2009-EA",
        "tileReference": "TQ46",
        "fileName": "LIDAR-DSM-50CM-2009-TQ4060.zip",
        "coverageLayer": "LIDAR-DSM-50CM-ENGLAND-2009-EA-MD-YY",
        "fileSize": 104601394,
        "descriptiveName": "LIDAR Tiles DSM at 50cm spatial resolution 2009",
        "description": "50cm",
        "groupName": "LIDAR-DSM-TIMESTAMPED-ENGLAND-2009-EA",
        "displayOrder": -50,
        "metaDataUrl": null,
        "url": "http:\/\/www.geostore.com\/environment-agency\/rest\/product\/download\/ed780b0e-b281-11e6-a8b2-9457a5578ca0"
    },
    {
        "id": 176856,
        "guid": "67f5f5bc-b282-11e6-a8b2-9457a5578ca0",
        "pyramid": "LIDAR-DSM-50CM-ENGLAND-2009-EA",
        "tileReference": "TQ46",
        "fileName": "LIDAR-DSM-50CM-2009-TQ4565.zip",
        "coverageLayer": "LIDAR-DSM-50CM-ENGLAND-2009-EA-MD-YY",
        "fileSize": 157717646,
        "descriptiveName": "LIDAR Tiles DSM at 50cm spatial resolution 2009",
        "description": "50cm",
        "groupName": "LIDAR-DSM-TIMESTAMPED-ENGLAND-2009-EA",
        "displayOrder": -50,
        "metaDataUrl": null,
        "url": "http:\/\/www.geostore.com\/environment-agency\/rest\/product\/download\/67f5f5bc-b282-11e6-a8b2-9457a5578ca0"
    },
    {
        "id": 176798,
        "guid": "39923f32-b282-11e6-a8b2-9457a5578ca0",
        "pyramid": "LIDAR-DSM-50CM-ENGLAND-2009-EA",
        "tileReference": "TQ46",
        "fileName": "LIDAR-DSM-50CM-2009-TQ4560.zip",
        "coverageLayer": "LIDAR-DSM-50CM-ENGLAND-2009-EA-MD-YY",
        "fileSize": 148886201,
        "descriptiveName": "LIDAR Tiles DSM at 50cm spatial resolution 2009",
        "description": "50cm",
        "groupName": "LIDAR-DSM-TIMESTAMPED-ENGLAND-2009-EA",
        "displayOrder": -50,
        "metaDataUrl": null,
        "url": "http:\/\/www.geostore.com\/environment-agency\/rest\/product\/download\/39923f32-b282-11e6-a8b2-9457a5578ca0"
    },
    {
        "id": 188480,
        "guid": "7909050c-b27c-11e6-9538-9457a5578ca0",
        "pyramid": "LIDAR-DSM-50CM-ENGLAND-2014-EA",
        "tileReference": "TQ46",
        "fileName": "LIDAR-DSM-50CM-2014-TQ4060.zip",
        "coverageLayer": "LIDAR-DSM-50CM-ENGLAND-2014-EA-MD-YY",
        "fileSize": 61330558,
        "descriptiveName": "LIDAR Tiles DSM at 50cm spatial resolution 2014",
        "description": "50cm",
        "groupName": "LIDAR-DSM-TIMESTAMPED-ENGLAND-2014-EA",
        "displayOrder": -50,
        "metaDataUrl": null,
        "url": "http:\/\/www.geostore.com\/environment-agency\/rest\/product\/download\/7909050c-b27c-11e6-9538-9457a5578ca0"
    },
    {
        "id": 188507,
        "guid": "a97e33ec-b27c-11e6-9538-9457a5578ca0",
        "pyramid": "LIDAR-DSM-50CM-ENGLAND-2014-EA",
        "tileReference": "TQ46",
        "fileName": "LIDAR-DSM-50CM-2014-TQ4065.zip",
        "coverageLayer": "LIDAR-DSM-50CM-ENGLAND-2014-EA-MD-YY",
        "fileSize": 165294326,
        "descriptiveName": "LIDAR Tiles DSM at 50cm spatial resolution 2014",
        "description": "50cm",
        "groupName": "LIDAR-DSM-TIMESTAMPED-ENGLAND-2014-EA",
        "displayOrder": -50,
        "metaDataUrl": null,
        "url": "http:\/\/www.geostore.com\/environment-agency\/rest\/product\/download\/a97e33ec-b27c-11e6-9538-9457a5578ca0"
    },
    {
        "id": 188640,
        "guid": "3947b476-b27d-11e6-9538-9457a5578ca0",
        "pyramid": "LIDAR-DSM-50CM-ENGLAND-2014-EA",
        "tileReference": "TQ46",
        "fileName": "LIDAR-DSM-50CM-2014-TQ4560.zip",
        "coverageLayer": "LIDAR-DSM-50CM-ENGLAND-2014-EA-MD-YY",
        "fileSize": 6603630,
        "descriptiveName": "LIDAR Tiles DSM at 50cm spatial resolution 2014",
        "description": "50cm",
        "groupName": "LIDAR-DSM-TIMESTAMPED-ENGLAND-2014-EA",
        "displayOrder": -50,
        "metaDataUrl": null,
        "url": "http:\/\/www.geostore.com\/environment-agency\/rest\/product\/download\/3947b476-b27d-11e6-9538-9457a5578ca0"
    },
    {
        "id": 188682,
        "guid": "48208432-b27d-11e6-9538-9457a5578ca0",
        "pyramid": "LIDAR-DSM-50CM-ENGLAND-2014-EA",
        "tileReference": "TQ46",
        "fileName": "LIDAR-DSM-50CM-2014-TQ4565.zip",
        "coverageLayer": "LIDAR-DSM-50CM-ENGLAND-2014-EA-MD-YY",
        "fileSize": 51791521,
        "descriptiveName": "LIDAR Tiles DSM at 50cm spatial resolution 2014",
        "description": "50cm",
        "groupName": "LIDAR-DSM-TIMESTAMPED-ENGLAND-2014-EA",
        "displayOrder": -50,
        "metaDataUrl": null,
        "url": "http:\/\/www.geostore.com\/environment-agency\/rest\/product\/download\/48208432-b27d-11e6-9538-9457a5578ca0"
    },
    {
        "id": 225548,
        "guid": "105d545e-a6b0-11e6-8f59-8cdcd4b4861c",
        "pyramid": "LIDAR-DSM-50CM-ENGLAND-EA",
        "tileReference": "TQ46",
        "fileName": "LIDAR-DSM-50CM-TQ4060.zip",
        "coverageLayer": "LIDAR-DSM-50CM-ENGLAND-EA-MD-YY",
        "fileSize": 136151812,
        "descriptiveName": "LIDAR Composite DSM - 50cm spatial resolution",
        "description": "DSM at 50cm spatial resolution",
        "groupName": "LIDAR-DSM-GROUP-ENGLAND-EA",
        "displayOrder": -50,
        "metaDataUrl": "https:\/\/data.gov.uk\/dataset\/lidar-composite-dsm-50cm1",
        "url": "http:\/\/www.geostore.com\/environment-agency\/rest\/product\/download\/105d545e-a6b0-11e6-8f59-8cdcd4b4861c"
    },
    {
        "id": 225557,
        "guid": "5e9f73b8-a6b0-11e6-8f59-8cdcd4b4861c",
        "pyramid": "LIDAR-DSM-50CM-ENGLAND-EA",
        "tileReference": "TQ46",
        "fileName": "LIDAR-DSM-50CM-TQ4065.zip",
        "coverageLayer": "LIDAR-DSM-50CM-ENGLAND-EA-MD-YY",
        "fileSize": 155725601,
        "descriptiveName": "LIDAR Composite DSM - 50cm spatial resolution",
        "description": "DSM at 50cm spatial resolution",
        "groupName": "LIDAR-DSM-GROUP-ENGLAND-EA",
        "displayOrder": -50,
        "metaDataUrl": "https:\/\/data.gov.uk\/dataset\/lidar-composite-dsm-50cm1",
        "url": "http:\/\/www.geostore.com\/environment-agency\/rest\/product\/download\/5e9f73b8-a6b0-11e6-8f59-8cdcd4b4861c"
    },
    {
        "id": 225637,
        "guid": "56b510d4-a6b2-11e6-8f59-8cdcd4b4861c",
        "pyramid": "LIDAR-DSM-50CM-ENGLAND-EA",
        "tileReference": "TQ46",
        "fileName": "LIDAR-DSM-50CM-TQ4560.zip",
        "coverageLayer": "LIDAR-DSM-50CM-ENGLAND-EA-MD-YY",
        "fileSize": 145069104,
        "descriptiveName": "LIDAR Composite DSM - 50cm spatial resolution",
        "description": "DSM at 50cm spatial resolution",
        "groupName": "LIDAR-DSM-GROUP-ENGLAND-EA",
        "displayOrder": -50,
        "metaDataUrl": "https:\/\/data.gov.uk\/dataset\/lidar-composite-dsm-50cm1",
        "url": "http:\/\/www.geostore.com\/environment-agency\/rest\/product\/download\/56b510d4-a6b2-11e6-8f59-8cdcd4b4861c"
    },
    {
        "id": 225645,
        "guid": "7c7569e0-a6b2-11e6-8f59-8cdcd4b4861c",
        "pyramid": "LIDAR-DSM-50CM-ENGLAND-EA",
        "tileReference": "TQ46",
        "fileName": "LIDAR-DSM-50CM-TQ4565.zip",
        "coverageLayer": "LIDAR-DSM-50CM-ENGLAND-EA-MD-YY",
        "fileSize": 151654625,
        "descriptiveName": "LIDAR Composite DSM - 50cm spatial resolution",
        "description": "DSM at 50cm spatial resolution",
        "groupName": "LIDAR-DSM-GROUP-ENGLAND-EA",
        "displayOrder": -50,
        "metaDataUrl": "https:\/\/data.gov.uk\/dataset\/lidar-composite-dsm-50cm1",
        "url": "http:\/\/www.geostore.com\/environment-agency\/rest\/product\/download\/7c7569e0-a6b2-11e6-8f59-8cdcd4b4861c"
    },
    {
        "id": 196474,
        "guid": "6eb0e712-b26f-11e6-a00b-9457a5578ca0",
        "pyramid": "LIDAR-DTM-1M-ENGLAND-2005-EA",
        "tileReference": "TQ46",
        "fileName": "LIDAR-DTM-1M-2005-TQ4065.zip",
        "coverageLayer": "LIDAR-DTM-1M-ENGLAND-2005-EA-MD-YY",
        "fileSize": 35310573,
        "descriptiveName": "LIDAR Tiles DTM at 1m spatial resolution 2005",
        "description": "1m",
        "groupName": "LIDAR-DTM-TIMESTAMPED-ENGLAND-2005-EA",
        "displayOrder": -100,
        "metaDataUrl": null,
        "url": "http:\/\/www.geostore.com\/environment-agency\/rest\/product\/download\/6eb0e712-b26f-11e6-a00b-9457a5578ca0"
    },
    {
        "id": 196483,
        "guid": "7a767594-b26f-11e6-a00b-9457a5578ca0",
        "pyramid": "LIDAR-DTM-1M-ENGLAND-2005-EA",
        "tileReference": "TQ46",
        "fileName": "LIDAR-DTM-1M-2005-TQ4565.zip",
        "coverageLayer": "LIDAR-DTM-1M-ENGLAND-2005-EA-MD-YY",
        "fileSize": 9545445,
        "descriptiveName": "LIDAR Tiles DTM at 1m spatial resolution 2005",
        "description": "1m",
        "groupName": "LIDAR-DTM-TIMESTAMPED-ENGLAND-2005-EA",
        "displayOrder": -100,
        "metaDataUrl": null,
        "url": "http:\/\/www.geostore.com\/environment-agency\/rest\/product\/download\/7a767594-b26f-11e6-a00b-9457a5578ca0"
    },
    {
        "id": 196481,
        "guid": "784ca81a-b26f-11e6-a00b-9457a5578ca0",
        "pyramid": "LIDAR-DTM-1M-ENGLAND-2005-EA",
        "tileReference": "TQ46",
        "fileName": "LIDAR-DTM-1M-2005-TQ4560.zip",
        "coverageLayer": "LIDAR-DTM-1M-ENGLAND-2005-EA-MD-YY",
        "fileSize": 2724126,
        "descriptiveName": "LIDAR Tiles DTM at 1m spatial resolution 2005",
        "description": "1m",
        "groupName": "LIDAR-DTM-TIMESTAMPED-ENGLAND-2005-EA",
        "displayOrder": -100,
        "metaDataUrl": null,
        "url": "http:\/\/www.geostore.com\/environment-agency\/rest\/product\/download\/784ca81a-b26f-11e6-a00b-9457a5578ca0"
    },
    {
        "id": 196468,
        "guid": "6763f616-b26f-11e6-a00b-9457a5578ca0",
        "pyramid": "LIDAR-DTM-1M-ENGLAND-2005-EA",
        "tileReference": "TQ46",
        "fileName": "LIDAR-DTM-1M-2005-TQ4060.zip",
        "coverageLayer": "LIDAR-DTM-1M-ENGLAND-2005-EA-MD-YY",
        "fileSize": 11384022,
        "descriptiveName": "LIDAR Tiles DTM at 1m spatial resolution 2005",
        "description": "1m",
        "groupName": "LIDAR-DTM-TIMESTAMPED-ENGLAND-2005-EA",
        "displayOrder": -100,
        "metaDataUrl": null,
        "url": "http:\/\/www.geostore.com\/environment-agency\/rest\/product\/download\/6763f616-b26f-11e6-a00b-9457a5578ca0"
    },
    {
        "id": 203499,
        "guid": "2dd78afa-703b-11e6-91b0-8cdcd4b4861c",
        "pyramid": "LIDAR-DTM-1M-ENGLAND-2012-EA",
        "tileReference": "TQ46",
        "fileName": "LIDAR-DTM-1M-2012-TQ4565.zip",
        "coverageLayer": "LIDAR-DTM-1M-ENGLAND-2012-EA-MD-YY",
        "fileSize": 13831757,
        "descriptiveName": "LIDAR Tiles DTM at 1m spatial resolution 2012",
        "description": "1m",
        "groupName": "LIDAR-DTM-TIMESTAMPED-ENGLAND-2012-EA",
        "displayOrder": -100,
        "metaDataUrl": null,
        "url": "http:\/\/www.geostore.com\/environment-agency\/rest\/product\/download\/2dd78afa-703b-11e6-91b0-8cdcd4b4861c"
    },
    {
        "id": 203460,
        "guid": "fd67c68c-703a-11e6-91b0-8cdcd4b4861c",
        "pyramid": "LIDAR-DTM-1M-ENGLAND-2012-EA",
        "tileReference": "TQ46",
        "fileName": "LIDAR-DTM-1M-2012-TQ4060.zip",
        "coverageLayer": "LIDAR-DTM-1M-ENGLAND-2012-EA-MD-YY",
        "fileSize": 18299511,
        "descriptiveName": "LIDAR Tiles DTM at 1m spatial resolution 2012",
        "description": "1m",
        "groupName": "LIDAR-DTM-TIMESTAMPED-ENGLAND-2012-EA",
        "displayOrder": -100,
        "metaDataUrl": null,
        "url": "http:\/\/www.geostore.com\/environment-agency\/rest\/product\/download\/fd67c68c-703a-11e6-91b0-8cdcd4b4861c"
    },
    {
        "id": 203495,
        "guid": "26bb66ec-703b-11e6-91b0-8cdcd4b4861c",
        "pyramid": "LIDAR-DTM-1M-ENGLAND-2012-EA",
        "tileReference": "TQ46",
        "fileName": "LIDAR-DTM-1M-2012-TQ4560.zip",
        "coverageLayer": "LIDAR-DTM-1M-ENGLAND-2012-EA-MD-YY",
        "fileSize": 3393193,
        "descriptiveName": "LIDAR Tiles DTM at 1m spatial resolution 2012",
        "description": "1m",
        "groupName": "LIDAR-DTM-TIMESTAMPED-ENGLAND-2012-EA",
        "displayOrder": -100,
        "metaDataUrl": null,
        "url": "http:\/\/www.geostore.com\/environment-agency\/rest\/product\/download\/26bb66ec-703b-11e6-91b0-8cdcd4b4861c"
    },
    {
        "id": 203468,
        "guid": "09582fcc-703b-11e6-91b0-8cdcd4b4861c",
        "pyramid": "LIDAR-DTM-1M-ENGLAND-2012-EA",
        "tileReference": "TQ46",
        "fileName": "LIDAR-DTM-1M-2012-TQ4065.zip",
        "coverageLayer": "LIDAR-DTM-1M-ENGLAND-2012-EA-MD-YY",
        "fileSize": 50320575,
        "descriptiveName": "LIDAR Tiles DTM at 1m spatial resolution 2012",
        "description": "1m",
        "groupName": "LIDAR-DTM-TIMESTAMPED-ENGLAND-2012-EA",
        "displayOrder": -100,
        "metaDataUrl": null,
        "url": "http:\/\/www.geostore.com\/environment-agency\/rest\/product\/download\/09582fcc-703b-11e6-91b0-8cdcd4b4861c"
    },
    {
        "id": 155156,
        "guid": "4c625382-a066-11e6-bdaa-8cdcd4b4861c",
        "pyramid": "LIDAR-DTM-1M-ENGLAND-2015-EA",
        "tileReference": "TQ46",
        "fileName": "LIDAR-DTM-1M-2015-TQ4560.zip",
        "coverageLayer": "LIDAR-DTM-1M-ENGLAND-2015-EA-MD-YY",
        "fileSize": 61994267,
        "descriptiveName": "LIDAR Tiles DTM at 1m spatial resolution 2015",
        "description": "1m",
        "groupName": "LIDAR-DTM-TIMESTAMPED-ENGLAND-2015-EA",
        "displayOrder": -100,
        "metaDataUrl": null,
        "url": "http:\/\/www.geostore.com\/environment-agency\/rest\/product\/download\/4c625382-a066-11e6-bdaa-8cdcd4b4861c"
    },
    {
        "id": 155131,
        "guid": "027bc2c6-a066-11e6-bdaa-8cdcd4b4861c",
        "pyramid": "LIDAR-DTM-1M-ENGLAND-2015-EA",
        "tileReference": "TQ46",
        "fileName": "LIDAR-DTM-1M-2015-TQ4060.zip",
        "coverageLayer": "LIDAR-DTM-1M-ENGLAND-2015-EA-MD-YY",
        "fileSize": 47639979,
        "descriptiveName": "LIDAR Tiles DTM at 1m spatial resolution 2015",
        "description": "1m",
        "groupName": "LIDAR-DTM-TIMESTAMPED-ENGLAND-2015-EA",
        "displayOrder": -100,
        "metaDataUrl": null,
        "url": "http:\/\/www.geostore.com\/environment-agency\/rest\/product\/download\/027bc2c6-a066-11e6-bdaa-8cdcd4b4861c"
    },
    {
        "id": 155134,
        "guid": "0c22ce8c-a066-11e6-bdaa-8cdcd4b4861c",
        "pyramid": "LIDAR-DTM-1M-ENGLAND-2015-EA",
        "tileReference": "TQ46",
        "fileName": "LIDAR-DTM-1M-2015-TQ4065.zip",
        "coverageLayer": "LIDAR-DTM-1M-ENGLAND-2015-EA-MD-YY",
        "fileSize": 38514667,
        "descriptiveName": "LIDAR Tiles DTM at 1m spatial resolution 2015",
        "description": "1m",
        "groupName": "LIDAR-DTM-TIMESTAMPED-ENGLAND-2015-EA",
        "displayOrder": -100,
        "metaDataUrl": null,
        "url": "http:\/\/www.geostore.com\/environment-agency\/rest\/product\/download\/0c22ce8c-a066-11e6-bdaa-8cdcd4b4861c"
    },
    {
        "id": 155157,
        "guid": "5b77fd18-a066-11e6-bdaa-8cdcd4b4861c",
        "pyramid": "LIDAR-DTM-1M-ENGLAND-2015-EA",
        "tileReference": "TQ46",
        "fileName": "LIDAR-DTM-1M-2015-TQ4565.zip",
        "coverageLayer": "LIDAR-DTM-1M-ENGLAND-2015-EA-MD-YY",
        "fileSize": 59965575,
        "descriptiveName": "LIDAR Tiles DTM at 1m spatial resolution 2015",
        "description": "1m",
        "groupName": "LIDAR-DTM-TIMESTAMPED-ENGLAND-2015-EA",
        "displayOrder": -100,
        "metaDataUrl": null,
        "url": "http:\/\/www.geostore.com\/environment-agency\/rest\/product\/download\/5b77fd18-a066-11e6-bdaa-8cdcd4b4861c"
    },
    {
        "id": 236815,
        "guid": "86c84dfc-ae20-11e6-9918-9457a5578ca0",
        "pyramid": "LIDAR-DTM-1M-ENGLAND-EA",
        "tileReference": "TQ46",
        "fileName": "LIDAR-DTM-1M-TQ4060.zip",
        "coverageLayer": "LIDAR-DTM-1M-ENGLAND-EA-MD-YY",
        "fileSize": 35970133,
        "descriptiveName": "LIDAR Composite DTM - 1m spatial resolution",
        "description": "DTM at 1m spatial resolution",
        "groupName": "LIDAR-DTM-GROUP-ENGLAND-EA",
        "displayOrder": -100,
        "metaDataUrl": "https:\/\/data.gov.uk\/dataset\/lidar-composite-dtm-1m1",
        "url": "http:\/\/www.geostore.com\/environment-agency\/rest\/product\/download\/86c84dfc-ae20-11e6-9918-9457a5578ca0"
    },
    {
        "id": 236859,
        "guid": "2e90e8e6-ae21-11e6-9918-9457a5578ca0",
        "pyramid": "LIDAR-DTM-1M-ENGLAND-EA",
        "tileReference": "TQ46",
        "fileName": "LIDAR-DTM-1M-TQ4565.zip",
        "coverageLayer": "LIDAR-DTM-1M-ENGLAND-EA-MD-YY",
        "fileSize": 48037724,
        "descriptiveName": "LIDAR Composite DTM - 1m spatial resolution",
        "description": "DTM at 1m spatial resolution",
        "groupName": "LIDAR-DTM-GROUP-ENGLAND-EA",
        "displayOrder": -100,
        "metaDataUrl": "https:\/\/data.gov.uk\/dataset\/lidar-composite-dtm-1m1",
        "url": "http:\/\/www.geostore.com\/environment-agency\/rest\/product\/download\/2e90e8e6-ae21-11e6-9918-9457a5578ca0"
    },
    {
        "id": 236857,
        "guid": "226bd076-ae21-11e6-9918-9457a5578ca0",
        "pyramid": "LIDAR-DTM-1M-ENGLAND-EA",
        "tileReference": "TQ46",
        "fileName": "LIDAR-DTM-1M-TQ4560.zip",
        "coverageLayer": "LIDAR-DTM-1M-ENGLAND-EA-MD-YY",
        "fileSize": 51544823,
        "descriptiveName": "LIDAR Composite DTM - 1m spatial resolution",
        "description": "DTM at 1m spatial resolution",
        "groupName": "LIDAR-DTM-GROUP-ENGLAND-EA",
        "displayOrder": -100,
        "metaDataUrl": "https:\/\/data.gov.uk\/dataset\/lidar-composite-dtm-1m1",
        "url": "http:\/\/www.geostore.com\/environment-agency\/rest\/product\/download\/226bd076-ae21-11e6-9918-9457a5578ca0"
    },
    {
        "id": 236818,
        "guid": "8bbd91a0-ae20-11e6-9918-9457a5578ca0",
        "pyramid": "LIDAR-DTM-1M-ENGLAND-EA",
        "tileReference": "TQ46",
        "fileName": "LIDAR-DTM-1M-TQ4065.zip",
        "coverageLayer": "LIDAR-DTM-1M-ENGLAND-EA-MD-YY",
        "fileSize": 18975434,
        "descriptiveName": "LIDAR Composite DTM - 1m spatial resolution",
        "description": "DTM at 1m spatial resolution",
        "groupName": "LIDAR-DTM-GROUP-ENGLAND-EA",
        "displayOrder": -100,
        "metaDataUrl": "https:\/\/data.gov.uk\/dataset\/lidar-composite-dtm-1m1",
        "url": "http:\/\/www.geostore.com\/environment-agency\/rest\/product\/download\/8bbd91a0-ae20-11e6-9918-9457a5578ca0"
    },
    {
        "id": 220856,
        "guid": "9a5c4168-a509-11e6-b183-9457a5578ca0",
        "pyramid": "LIDAR-DTM-2M-ENGLAND-EA",
        "tileReference": "TQ46",
        "fileName": "LIDAR-DTM-2M-TQ4065.zip",
        "coverageLayer": "LIDAR-DTM-2M-ENGLAND-EA-MD-YY",
        "fileSize": 13799987,
        "descriptiveName": "LIDAR Composite DTM - 2m spatial resolution",
        "description": "DTM at 2m spatial resolution",
        "groupName": "LIDAR-DTM-GROUP-ENGLAND-EA",
        "displayOrder": -200,
        "metaDataUrl": "https:\/\/data.gov.uk\/dataset\/lidar-composite-dtm-2m1",
        "url": "http:\/\/www.geostore.com\/environment-agency\/rest\/product\/download\/9a5c4168-a509-11e6-b183-9457a5578ca0"
    },
    {
        "id": 220986,
        "guid": "8108c3fc-a50a-11e6-b183-9457a5578ca0",
        "pyramid": "LIDAR-DTM-2M-ENGLAND-EA",
        "tileReference": "TQ46",
        "fileName": "LIDAR-DTM-2M-TQ4560.zip",
        "coverageLayer": "LIDAR-DTM-2M-ENGLAND-EA-MD-YY",
        "fileSize": 13882947,
        "descriptiveName": "LIDAR Composite DTM - 2m spatial resolution",
        "description": "DTM at 2m spatial resolution",
        "groupName": "LIDAR-DTM-GROUP-ENGLAND-EA",
        "displayOrder": -200,
        "metaDataUrl": "https:\/\/data.gov.uk\/dataset\/lidar-composite-dtm-2m1",
        "url": "http:\/\/www.geostore.com\/environment-agency\/rest\/product\/download\/8108c3fc-a50a-11e6-b183-9457a5578ca0"
    },
    {
        "id": 220991,
        "guid": "8675fdfa-a50a-11e6-b183-9457a5578ca0",
        "pyramid": "LIDAR-DTM-2M-ENGLAND-EA",
        "tileReference": "TQ46",
        "fileName": "LIDAR-DTM-2M-TQ4565.zip",
        "coverageLayer": "LIDAR-DTM-2M-ENGLAND-EA-MD-YY",
        "fileSize": 13458520,
        "descriptiveName": "LIDAR Composite DTM - 2m spatial resolution",
        "description": "DTM at 2m spatial resolution",
        "groupName": "LIDAR-DTM-GROUP-ENGLAND-EA",
        "displayOrder": -200,
        "metaDataUrl": "https:\/\/data.gov.uk\/dataset\/lidar-composite-dtm-2m1",
        "url": "http:\/\/www.geostore.com\/environment-agency\/rest\/product\/download\/8675fdfa-a50a-11e6-b183-9457a5578ca0"
    },
    {
        "id": 220853,
        "guid": "96040808-a509-11e6-b183-9457a5578ca0",
        "pyramid": "LIDAR-DTM-2M-ENGLAND-EA",
        "tileReference": "TQ46",
        "fileName": "LIDAR-DTM-2M-TQ4060.zip",
        "coverageLayer": "LIDAR-DTM-2M-ENGLAND-EA-MD-YY",
        "fileSize": 12106076,
        "descriptiveName": "LIDAR Composite DTM - 2m spatial resolution",
        "description": "DTM at 2m spatial resolution",
        "groupName": "LIDAR-DTM-GROUP-ENGLAND-EA",
        "displayOrder": -200,
        "metaDataUrl": "https:\/\/data.gov.uk\/dataset\/lidar-composite-dtm-2m1",
        "url": "http:\/\/www.geostore.com\/environment-agency\/rest\/product\/download\/96040808-a509-11e6-b183-9457a5578ca0"
    },
    {
        "id": 178973,
        "guid": "88621b02-b276-11e6-909f-9457a5578ca0",
        "pyramid": "LIDAR-DTM-50CM-ENGLAND-2009-EA",
        "tileReference": "TQ46",
        "fileName": "LIDAR-DTM-50CM-2009-TQ4060.zip",
        "coverageLayer": "LIDAR-DTM-50CM-ENGLAND-2009-EA-MD-YY",
        "fileSize": 94563277,
        "descriptiveName": "LIDAR Tiles DTM at 50cm spatial resolution 2009",
        "description": "50cm",
        "groupName": "LIDAR-DTM-TIMESTAMPED-ENGLAND-2009-EA",
        "displayOrder": -50,
        "metaDataUrl": null,
        "url": "http:\/\/www.geostore.com\/environment-agency\/rest\/product\/download\/88621b02-b276-11e6-909f-9457a5578ca0"
    },
    {
        "id": 178978,
        "guid": "8e4ce420-b276-11e6-909f-9457a5578ca0",
        "pyramid": "LIDAR-DTM-50CM-ENGLAND-2009-EA",
        "tileReference": "TQ46",
        "fileName": "LIDAR-DTM-50CM-2009-TQ4065.zip",
        "coverageLayer": "LIDAR-DTM-50CM-ENGLAND-2009-EA-MD-YY",
        "fileSize": 16539580,
        "descriptiveName": "LIDAR Tiles DTM at 50cm spatial resolution 2009",
        "description": "50cm",
        "groupName": "LIDAR-DTM-TIMESTAMPED-ENGLAND-2009-EA",
        "displayOrder": -50,
        "metaDataUrl": null,
        "url": "http:\/\/www.geostore.com\/environment-agency\/rest\/product\/download\/8e4ce420-b276-11e6-909f-9457a5578ca0"
    },
    {
        "id": 179140,
        "guid": "d64d4a12-b276-11e6-909f-9457a5578ca0",
        "pyramid": "LIDAR-DTM-50CM-ENGLAND-2009-EA",
        "tileReference": "TQ46",
        "fileName": "LIDAR-DTM-50CM-2009-TQ4560.zip",
        "coverageLayer": "LIDAR-DTM-50CM-ENGLAND-2009-EA-MD-YY",
        "fileSize": 133454892,
        "descriptiveName": "LIDAR Tiles DTM at 50cm spatial resolution 2009",
        "description": "50cm",
        "groupName": "LIDAR-DTM-TIMESTAMPED-ENGLAND-2009-EA",
        "displayOrder": -50,
        "metaDataUrl": null,
        "url": "http:\/\/www.geostore.com\/environment-agency\/rest\/product\/download\/d64d4a12-b276-11e6-909f-9457a5578ca0"
    },
    {
        "id": 179197,
        "guid": "fe74cb64-b276-11e6-909f-9457a5578ca0",
        "pyramid": "LIDAR-DTM-50CM-ENGLAND-2009-EA",
        "tileReference": "TQ46",
        "fileName": "LIDAR-DTM-50CM-2009-TQ4565.zip",
        "coverageLayer": "LIDAR-DTM-50CM-ENGLAND-2009-EA-MD-YY",
        "fileSize": 135161826,
        "descriptiveName": "LIDAR Tiles DTM at 50cm spatial resolution 2009",
        "description": "50cm",
        "groupName": "LIDAR-DTM-TIMESTAMPED-ENGLAND-2009-EA",
        "displayOrder": -50,
        "metaDataUrl": null,
        "url": "http:\/\/www.geostore.com\/environment-agency\/rest\/product\/download\/fe74cb64-b276-11e6-909f-9457a5578ca0"
    },
    {
        "id": 188968,
        "guid": "ea9164bc-b29a-11e6-85ee-9457a5578ca0",
        "pyramid": "LIDAR-DTM-50CM-ENGLAND-2014-EA",
        "tileReference": "TQ46",
        "fileName": "LIDAR-DTM-50CM-2014-TQ4560.zip",
        "coverageLayer": "LIDAR-DTM-50CM-ENGLAND-2014-EA-MD-YY",
        "fileSize": 5522803,
        "descriptiveName": "LIDAR Tiles DTM at 50cm spatial resolution 2014",
        "description": "50cm",
        "groupName": "LIDAR-DTM-TIMESTAMPED-ENGLAND-2014-EA",
        "displayOrder": -50,
        "metaDataUrl": null,
        "url": "http:\/\/www.geostore.com\/environment-agency\/rest\/product\/download\/ea9164bc-b29a-11e6-85ee-9457a5578ca0"
    },
    {
        "id": 188985,
        "guid": "f667ee78-b29a-11e6-85ee-9457a5578ca0",
        "pyramid": "LIDAR-DTM-50CM-ENGLAND-2014-EA",
        "tileReference": "TQ46",
        "fileName": "LIDAR-DTM-50CM-2014-TQ4565.zip",
        "coverageLayer": "LIDAR-DTM-50CM-ENGLAND-2014-EA-MD-YY",
        "fileSize": 41473493,
        "descriptiveName": "LIDAR Tiles DTM at 50cm spatial resolution 2014",
        "description": "50cm",
        "groupName": "LIDAR-DTM-TIMESTAMPED-ENGLAND-2014-EA",
        "displayOrder": -50,
        "metaDataUrl": null,
        "url": "http:\/\/www.geostore.com\/environment-agency\/rest\/product\/download\/f667ee78-b29a-11e6-85ee-9457a5578ca0"
    },
    {
        "id": 188786,
        "guid": "5a795c54-b29a-11e6-85ee-9457a5578ca0",
        "pyramid": "LIDAR-DTM-50CM-ENGLAND-2014-EA",
        "tileReference": "TQ46",
        "fileName": "LIDAR-DTM-50CM-2014-TQ4060.zip",
        "coverageLayer": "LIDAR-DTM-50CM-ENGLAND-2014-EA-MD-YY",
        "fileSize": 53136916,
        "descriptiveName": "LIDAR Tiles DTM at 50cm spatial resolution 2014",
        "description": "50cm",
        "groupName": "LIDAR-DTM-TIMESTAMPED-ENGLAND-2014-EA",
        "displayOrder": -50,
        "metaDataUrl": null,
        "url": "http:\/\/www.geostore.com\/environment-agency\/rest\/product\/download\/5a795c54-b29a-11e6-85ee-9457a5578ca0"
    },
    {
        "id": 188817,
        "guid": "7f007c38-b29a-11e6-85ee-9457a5578ca0",
        "pyramid": "LIDAR-DTM-50CM-ENGLAND-2014-EA",
        "tileReference": "TQ46",
        "fileName": "LIDAR-DTM-50CM-2014-TQ4065.zip",
        "coverageLayer": "LIDAR-DTM-50CM-ENGLAND-2014-EA-MD-YY",
        "fileSize": 128648277,
        "descriptiveName": "LIDAR Tiles DTM at 50cm spatial resolution 2014",
        "description": "50cm",
        "groupName": "LIDAR-DTM-TIMESTAMPED-ENGLAND-2014-EA",
        "displayOrder": -50,
        "metaDataUrl": null,
        "url": "http:\/\/www.geostore.com\/environment-agency\/rest\/product\/download\/7f007c38-b29a-11e6-85ee-9457a5578ca0"
    },
    {
        "id": 225185,
        "guid": "5b5fcdf6-a6a6-11e6-a7a9-9457a5578ca0",
        "pyramid": "LIDAR-DTM-50CM-ENGLAND-EA",
        "tileReference": "TQ46",
        "fileName": "LIDAR-DTM-50CM-TQ4065.zip",
        "coverageLayer": "LIDAR-DTM-50CM-ENGLAND-EA-MD-YY",
        "fileSize": 116401297,
        "descriptiveName": "LIDAR Composite DTM - 50cm spatial resolution",
        "description": "DTM at 50cm spatial resolution",
        "groupName": "LIDAR-DTM-GROUP-ENGLAND-EA",
        "displayOrder": -50,
        "metaDataUrl": "https:\/\/data.gov.uk\/dataset\/lidar-composite-dtm-50cm1",
        "url": "http:\/\/www.geostore.com\/environment-agency\/rest\/product\/download\/5b5fcdf6-a6a6-11e6-a7a9-9457a5578ca0"
    },
    {
        "id": 225261,
        "guid": "36be2d6a-a6a8-11e6-a7a9-9457a5578ca0",
        "pyramid": "LIDAR-DTM-50CM-ENGLAND-EA",
        "tileReference": "TQ46",
        "fileName": "LIDAR-DTM-50CM-TQ4565.zip",
        "coverageLayer": "LIDAR-DTM-50CM-ENGLAND-EA-MD-YY",
        "fileSize": 124549020,
        "descriptiveName": "LIDAR Composite DTM - 50cm spatial resolution",
        "description": "DTM at 50cm spatial resolution",
        "groupName": "LIDAR-DTM-GROUP-ENGLAND-EA",
        "displayOrder": -50,
        "metaDataUrl": "https:\/\/data.gov.uk\/dataset\/lidar-composite-dtm-50cm1",
        "url": "http:\/\/www.geostore.com\/environment-agency\/rest\/product\/download\/36be2d6a-a6a8-11e6-a7a9-9457a5578ca0"
    },
    {
        "id": 225257,
        "guid": "16799f94-a6a8-11e6-a7a9-9457a5578ca0",
        "pyramid": "LIDAR-DTM-50CM-ENGLAND-EA",
        "tileReference": "TQ46",
        "fileName": "LIDAR-DTM-50CM-TQ4560.zip",
        "coverageLayer": "LIDAR-DTM-50CM-ENGLAND-EA-MD-YY",
        "fileSize": 128200844,
        "descriptiveName": "LIDAR Composite DTM - 50cm spatial resolution",
        "description": "DTM at 50cm spatial resolution",
        "groupName": "LIDAR-DTM-GROUP-ENGLAND-EA",
        "displayOrder": -50,
        "metaDataUrl": "https:\/\/data.gov.uk\/dataset\/lidar-composite-dtm-50cm1",
        "url": "http:\/\/www.geostore.com\/environment-agency\/rest\/product\/download\/16799f94-a6a8-11e6-a7a9-9457a5578ca0"
    },
    {
        "id": 225182,
        "guid": "3c5d2cd2-a6a6-11e6-a7a9-9457a5578ca0",
        "pyramid": "LIDAR-DTM-50CM-ENGLAND-EA",
        "tileReference": "TQ46",
        "fileName": "LIDAR-DTM-50CM-TQ4060.zip",
        "coverageLayer": "LIDAR-DTM-50CM-ENGLAND-EA-MD-YY",
        "fileSize": 120083925,
        "descriptiveName": "LIDAR Composite DTM - 50cm spatial resolution",
        "description": "DTM at 50cm spatial resolution",
        "groupName": "LIDAR-DTM-GROUP-ENGLAND-EA",
        "displayOrder": -50,
        "metaDataUrl": "https:\/\/data.gov.uk\/dataset\/lidar-composite-dtm-50cm1",
        "url": "http:\/\/www.geostore.com\/environment-agency\/rest\/product\/download\/3c5d2cd2-a6a6-11e6-a7a9-9457a5578ca0"
    },
    {
        "id": 162231,
        "guid": "a1714d2c-6bfc-11e6-bd27-9457a5578ca0",
        "pyramid": "LIDAR-LAZ-ENGLAND-2009-EA",
        "tileReference": "TQ46",
        "fileName": "LIDAR-LAZ-2009-TQ4565.zip",
        "coverageLayer": "LIDAR-LAZ-ENGLAND-2009-EA-MD-YY",
        "fileSize": 364403289,
        "descriptiveName": "LIDAR Point Cloud 2009",
        "description": "2009",
        "groupName": "LIDAR-LAZ-ENGLAND-EA",
        "displayOrder": -2009,
        "metaDataUrl": null,
        "url": "http:\/\/www.geostore.com\/environment-agency\/rest\/product\/download\/a1714d2c-6bfc-11e6-bd27-9457a5578ca0"
    },
    {
        "id": 162230,
        "guid": "9a54a11a-6bfc-11e6-bd27-9457a5578ca0",
        "pyramid": "LIDAR-LAZ-ENGLAND-2009-EA",
        "tileReference": "TQ46",
        "fileName": "LIDAR-LAZ-2009-TQ4560.zip",
        "coverageLayer": "LIDAR-LAZ-ENGLAND-2009-EA-MD-YY",
        "fileSize": 323970988,
        "descriptiveName": "LIDAR Point Cloud 2009",
        "description": "2009",
        "groupName": "LIDAR-LAZ-ENGLAND-EA",
        "displayOrder": -2009,
        "metaDataUrl": null,
        "url": "http:\/\/www.geostore.com\/environment-agency\/rest\/product\/download\/9a54a11a-6bfc-11e6-bd27-9457a5578ca0"
    },
    {
        "id": 162200,
        "guid": "6be71420-6bfc-11e6-bd27-9457a5578ca0",
        "pyramid": "LIDAR-LAZ-ENGLAND-2009-EA",
        "tileReference": "TQ46",
        "fileName": "LIDAR-LAZ-2009-TQ4065.zip",
        "coverageLayer": "LIDAR-LAZ-ENGLAND-2009-EA-MD-YY",
        "fileSize": 55273504,
        "descriptiveName": "LIDAR Point Cloud 2009",
        "description": "2009",
        "groupName": "LIDAR-LAZ-ENGLAND-EA",
        "displayOrder": -2009,
        "metaDataUrl": null,
        "url": "http:\/\/www.geostore.com\/environment-agency\/rest\/product\/download\/6be71420-6bfc-11e6-bd27-9457a5578ca0"
    },
    {
        "id": 162199,
        "guid": "6abfa350-6bfc-11e6-bd27-9457a5578ca0",
        "pyramid": "LIDAR-LAZ-ENGLAND-2009-EA",
        "tileReference": "TQ46",
        "fileName": "LIDAR-LAZ-2009-TQ4060.zip",
        "coverageLayer": "LIDAR-LAZ-ENGLAND-2009-EA-MD-YY",
        "fileSize": 247298158,
        "descriptiveName": "LIDAR Point Cloud 2009",
        "description": "2009",
        "groupName": "LIDAR-LAZ-ENGLAND-EA",
        "displayOrder": -2009,
        "metaDataUrl": null,
        "url": "http:\/\/www.geostore.com\/environment-agency\/rest\/product\/download\/6abfa350-6bfc-11e6-bd27-9457a5578ca0"
    },
    {
        "id": 166313,
        "guid": "8409ed50-6c12-11e6-8e05-9457a5578ca0",
        "pyramid": "LIDAR-LAZ-ENGLAND-2012-EA",
        "tileReference": "TQ46",
        "fileName": "LIDAR-LAZ-2012-TQ4565.zip",
        "coverageLayer": "LIDAR-LAZ-ENGLAND-2012-EA-MD-YY",
        "fileSize": 13248970,
        "descriptiveName": "LIDAR Point Cloud 2012",
        "description": "2012",
        "groupName": "LIDAR-LAZ-ENGLAND-EA",
        "displayOrder": -2012,
        "metaDataUrl": null,
        "url": "http:\/\/www.geostore.com\/environment-agency\/rest\/product\/download\/8409ed50-6c12-11e6-8e05-9457a5578ca0"
    },
    {
        "id": 166295,
        "guid": "57a90d40-6c12-11e6-8e05-9457a5578ca0",
        "pyramid": "LIDAR-LAZ-ENGLAND-2012-EA",
        "tileReference": "TQ46",
        "fileName": "LIDAR-LAZ-2012-TQ4065.zip",
        "coverageLayer": "LIDAR-LAZ-ENGLAND-2012-EA-MD-YY",
        "fileSize": 116290882,
        "descriptiveName": "LIDAR Point Cloud 2012",
        "description": "2012",
        "groupName": "LIDAR-LAZ-ENGLAND-EA",
        "displayOrder": -2012,
        "metaDataUrl": null,
        "url": "http:\/\/www.geostore.com\/environment-agency\/rest\/product\/download\/57a90d40-6c12-11e6-8e05-9457a5578ca0"
    },
    {
        "id": 166294,
        "guid": "5565945e-6c12-11e6-8e05-9457a5578ca0",
        "pyramid": "LIDAR-LAZ-ENGLAND-2012-EA",
        "tileReference": "TQ46",
        "fileName": "LIDAR-LAZ-2012-TQ4060.zip",
        "coverageLayer": "LIDAR-LAZ-ENGLAND-2012-EA-MD-YY",
        "fileSize": 25127449,
        "descriptiveName": "LIDAR Point Cloud 2012",
        "description": "2012",
        "groupName": "LIDAR-LAZ-ENGLAND-EA",
        "displayOrder": -2012,
        "metaDataUrl": null,
        "url": "http:\/\/www.geostore.com\/environment-agency\/rest\/product\/download\/5565945e-6c12-11e6-8e05-9457a5578ca0"
    },
    {
        "id": 166312,
        "guid": "83b0c0f4-6c12-11e6-8e05-9457a5578ca0",
        "pyramid": "LIDAR-LAZ-ENGLAND-2012-EA",
        "tileReference": "TQ46",
        "fileName": "LIDAR-LAZ-2012-TQ4560.zip",
        "coverageLayer": "LIDAR-LAZ-ENGLAND-2012-EA-MD-YY",
        "fileSize": 8306,
        "descriptiveName": "LIDAR Point Cloud 2012",
        "description": "2012",
        "groupName": "LIDAR-LAZ-ENGLAND-EA",
        "displayOrder": -2012,
        "metaDataUrl": null,
        "url": "http:\/\/www.geostore.com\/environment-agency\/rest\/product\/download\/83b0c0f4-6c12-11e6-8e05-9457a5578ca0"
    },
    {
        "id": 168014,
        "guid": "52484ff2-6c1f-11e6-94ce-9457a5578ca0",
        "pyramid": "LIDAR-LAZ-ENGLAND-2014-EA",
        "tileReference": "TQ46",
        "fileName": "LIDAR-LAZ-2014-TQ4060.zip",
        "coverageLayer": "LIDAR-LAZ-ENGLAND-2014-EA-MD-YY",
        "fileSize": 223551587,
        "descriptiveName": "LIDAR Point Cloud 2014",
        "description": "2014",
        "groupName": "LIDAR-LAZ-ENGLAND-EA",
        "displayOrder": -2014,
        "metaDataUrl": null,
        "url": "http:\/\/www.geostore.com\/environment-agency\/rest\/product\/download\/52484ff2-6c1f-11e6-94ce-9457a5578ca0"
    },
    {
        "id": 153748,
        "guid": "90dd0640-6c1f-11e6-94ce-9457a5578ca0",
        "pyramid": "LIDAR-LAZ-ENGLAND-2014-EA",
        "tileReference": "TQ46",
        "fileName": "LIDAR-LAZ-2014-TQ4565.zip",
        "coverageLayer": "LIDAR-LAZ-ENGLAND-2014-EA-MD-YY",
        "fileSize": 226697762,
        "descriptiveName": "LIDAR Point Cloud 2014",
        "description": "2014",
        "groupName": "LIDAR-LAZ-ENGLAND-EA",
        "displayOrder": -2014,
        "metaDataUrl": null,
        "url": "http:\/\/www.geostore.com\/environment-agency\/rest\/product\/download\/90dd0640-6c1f-11e6-94ce-9457a5578ca0"
    },
    {
        "id": 168015,
        "guid": "5d2162a6-6c1f-11e6-94ce-9457a5578ca0",
        "pyramid": "LIDAR-LAZ-ENGLAND-2014-EA",
        "tileReference": "TQ46",
        "fileName": "LIDAR-LAZ-2014-TQ4065.zip",
        "coverageLayer": "LIDAR-LAZ-ENGLAND-2014-EA-MD-YY",
        "fileSize": 630664996,
        "descriptiveName": "LIDAR Point Cloud 2014",
        "description": "2014",
        "groupName": "LIDAR-LAZ-ENGLAND-EA",
        "displayOrder": -2014,
        "metaDataUrl": null,
        "url": "http:\/\/www.geostore.com\/environment-agency\/rest\/product\/download\/5d2162a6-6c1f-11e6-94ce-9457a5578ca0"
    },
    {
        "id": 153747,
        "guid": "8cb7ac00-6c1f-11e6-94ce-9457a5578ca0",
        "pyramid": "LIDAR-LAZ-ENGLAND-2014-EA",
        "tileReference": "TQ46",
        "fileName": "LIDAR-LAZ-2014-TQ4560.zip",
        "coverageLayer": "LIDAR-LAZ-ENGLAND-2014-EA-MD-YY",
        "fileSize": 27726443,
        "descriptiveName": "LIDAR Point Cloud 2014",
        "description": "2014",
        "groupName": "LIDAR-LAZ-ENGLAND-EA",
        "displayOrder": -2014,
        "metaDataUrl": null,
        "url": "http:\/\/www.geostore.com\/environment-agency\/rest\/product\/download\/8cb7ac00-6c1f-11e6-94ce-9457a5578ca0"
    },
    {
        "id": 154686,
        "guid": "1ea0c134-6af8-11e6-9ff7-8cdcd4b4861c",
        "pyramid": "LIDAR-LAZ-ENGLAND-2015-EA",
        "tileReference": "TQ46",
        "fileName": "LIDAR-LAZ-2015-TQ4565.zip",
        "coverageLayer": "LIDAR-LAZ-ENGLAND-2015-EA-MD-YY",
        "fileSize": 288982358,
        "descriptiveName": "LIDAR Point Cloud 2015",
        "description": "2015",
        "groupName": "LIDAR-LAZ-ENGLAND-EA",
        "displayOrder": -2015,
        "metaDataUrl": null,
        "url": "http:\/\/www.geostore.com\/environment-agency\/rest\/product\/download\/1ea0c134-6af8-11e6-9ff7-8cdcd4b4861c"
    },
    {
        "id": 154667,
        "guid": "e1f4bd44-6af7-11e6-9ff7-8cdcd4b4861c",
        "pyramid": "LIDAR-LAZ-ENGLAND-2015-EA",
        "tileReference": "TQ46",
        "fileName": "LIDAR-LAZ-2015-TQ4065.zip",
        "coverageLayer": "LIDAR-LAZ-ENGLAND-2015-EA-MD-YY",
        "fileSize": 234535802,
        "descriptiveName": "LIDAR Point Cloud 2015",
        "description": "2015",
        "groupName": "LIDAR-LAZ-ENGLAND-EA",
        "displayOrder": -2015,
        "metaDataUrl": null,
        "url": "http:\/\/www.geostore.com\/environment-agency\/rest\/product\/download\/e1f4bd44-6af7-11e6-9ff7-8cdcd4b4861c"
    },
    {
        "id": 154666,
        "guid": "dc7f54b4-6af7-11e6-9ff7-8cdcd4b4861c",
        "pyramid": "LIDAR-LAZ-ENGLAND-2015-EA",
        "tileReference": "TQ46",
        "fileName": "LIDAR-LAZ-2015-TQ4060.zip",
        "coverageLayer": "LIDAR-LAZ-ENGLAND-2015-EA-MD-YY",
        "fileSize": 245905532,
        "descriptiveName": "LIDAR Point Cloud 2015",
        "description": "2015",
        "groupName": "LIDAR-LAZ-ENGLAND-EA",
        "displayOrder": -2015,
        "metaDataUrl": null,
        "url": "http:\/\/www.geostore.com\/environment-agency\/rest\/product\/download\/dc7f54b4-6af7-11e6-9ff7-8cdcd4b4861c"
    },
    {
        "id": 154685,
        "guid": "1667fd02-6af8-11e6-9ff7-8cdcd4b4861c",
        "pyramid": "LIDAR-LAZ-ENGLAND-2015-EA",
        "tileReference": "TQ46",
        "fileName": "LIDAR-LAZ-2015-TQ4560.zip",
        "coverageLayer": "LIDAR-LAZ-ENGLAND-2015-EA-MD-YY",
        "fileSize": 315863850,
        "descriptiveName": "LIDAR Point Cloud 2015",
        "description": "2015",
        "groupName": "LIDAR-LAZ-ENGLAND-EA",
        "displayOrder": -2015,
        "metaDataUrl": null,
        "url": "http:\/\/www.geostore.com\/environment-agency\/rest\/product\/download\/1667fd02-6af8-11e6-9ff7-8cdcd4b4861c"
    },
    {
        "id": 149423,
        "guid": "58e933e8-3a93-11e6-ae4d-9457a5578ca0",
        "pyramid": "VAP-RGB-10CM-ENGLAND-2011-EA",
        "tileReference": "TQ46",
        "fileName": "Ortho-RGB-10CM-2011-TQ46NE.zip",
        "coverageLayer": "VAP-RGB-10CM-ENGLAND-2011-EA-MD-YY",
        "fileSize": 113254683,
        "descriptiveName": "VAP Tiles RGB at 10cm spatial resolution 2011",
        "description": "10cm",
        "groupName": "VAP-RGB-ENGLAND-2011-EA",
        "displayOrder": -100,
        "metaDataUrl": null,
        "url": "http:\/\/www.geostore.com\/environment-agency\/rest\/product\/download\/58e933e8-3a93-11e6-ae4d-9457a5578ca0"
    }
]